easy_sql/__init__.py
easy_sql/easy_manager.py
easy_sql/easy_mysql_dao_base.py
easy_sql/easy_util.py
easy_sql/mysql_config.py
easy_sql/mysql_log.py
easy_sql-0.0.4.dist-info/METADATA
easy_sql-0.0.4.dist-info/WHEEL
easy_sql-0.0.4.dist-info/top_level.txt
easy_sql-0.0.4.dist-info/RECORD
