Metadata-Version: 2.1
Name: easy-sql
Version: 0.0.4
Summary: easy to use mysql(kb)
Home-page: https://github.com/ksust/easy_sql
Author: ksust
Author-email: admin@ksust.com
Maintainer: ksust
Maintainer-email: admin@ksust.com
License: UNKNOWN
Platform: all
Classifier: Programming Language :: Python :: 3
Classifier: Programming Language :: Python :: 3.5
Classifier: Programming Language :: Python :: 3.6
Classifier: Programming Language :: Python :: 3.7
Classifier: Programming Language :: Python :: 3.8
Requires-Dist: SQLAlchemy (==1.3.13)
Requires-Dist: PyYAML (==5.3.1)
